flask_obfuscate/__init__.py
flask_obfuscate/obfuscate.py
tests/__init__.py
tests/test_obfuscate.py
Flask_Obfuscate-0.2.dist-info/METADATA
Flask_Obfuscate-0.2.dist-info/WHEEL
Flask_Obfuscate-0.2.dist-info/top_level.txt
Flask_Obfuscate-0.2.dist-info/RECORD
