Metadata-Version: 2.1
Name: Flask-Obfuscate
Version: 0.2
Summary: A Flask extension to obfuscate HTML responses.
Home-page: https://github.com/Lagden-Development/flask-obfuscate
Author: Zachariah Michael Lagden
Author-email: zach@zachlagden.uk
Classifier: Development Status :: 3 - Alpha
Classifier: Intended Audience :: Developers
Classifier: License :: OSI Approved :: MIT License
Classifier: Programming Language :: Python :: 3
Classifier: Programming Language :: Python :: 3.7
Classifier: Programming Language :: Python :: 3.8
Classifier: Programming Language :: Python :: 3.9
Classifier: Framework :: Flask
Requires-Dist: Flask
